{
  "meta": {
    "source": "AI: Z-Image ControlNet pose-source pipeline (tools/gen-frames.ts + pack-clips.cjs)",
    "cellWidth": 256,
    "cellHeight": 256
  },
  "animations": {
    "attack": {
      "strip": "animations/attack.png",
      "frameCount": 4,
      "frameWidth": 256,
      "frameHeight": 256,
      "sourceCells": [
        [
          0,
          0
        ],
        [
          1,
          0
        ],
        [
          2,
          0
        ],
        [
          3,
          0
        ]
      ]
    },
    "bair": {
      "strip": "animations/bair.png",
      "frameCount": 3,
      "frameWidth": 256,
      "frameHeight": 256,
      "sourceCells": [
        [
          0,
          0
        ],
        [
          1,
          0
        ],
        [
          2,
          0
        ]
      ]
    },
    "bthrow": {
      "strip": "animations/bthrow.png",
      "frameCount": 3,
      "frameWidth": 256,
      "frameHeight": 256,
      "sourceCells": [
        [
          0,
          0
        ],
        [
          1,
          0
        ],
        [
          2,
          0
        ]
      ]
    },
    "crouch": {
      "strip": "animations/crouch.png",
      "frameCount": 1,
      "frameWidth": 256,
      "frameHeight": 256,
      "sourceCells": [
        [
          0,
          0
        ]
      ]
    },
    "dair": {
      "strip": "animations/dair.png",
      "frameCount": 3,
      "frameWidth": 256,
      "frameHeight": 256,
      "sourceCells": [
        [
          0,
          0
        ],
        [
          1,
          0
        ],
        [
          2,
          0
        ]
      ]
    },
    "down_special": {
      "strip": "animations/down_special.png",
      "frameCount": 3,
      "frameWidth": 256,
      "frameHeight": 256,
      "sourceCells": [
        [
          0,
          0
        ],
        [
          1,
          0
        ],
        [
          2,
          0
        ]
      ]
    },
    "dthrow": {
      "strip": "animations/dthrow.png",
      "frameCount": 3,
      "frameWidth": 256,
      "frameHeight": 256,
      "sourceCells": [
        [
          0,
          0
        ],
        [
          1,
          0
        ],
        [
          2,
          0
        ]
      ]
    },
    "dtilt": {
      "strip": "animations/dtilt.png",
      "frameCount": 4,
      "frameWidth": 256,
      "frameHeight": 256,
      "sourceCells": [
        [
          0,
          0
        ],
        [
          1,
          0
        ],
        [
          2,
          0
        ],
        [
          3,
          0
        ]
      ]
    },
    "fair": {
      "strip": "animations/fair.png",
      "frameCount": 3,
      "frameWidth": 256,
      "frameHeight": 256,
      "sourceCells": [
        [
          0,
          0
        ],
        [
          1,
          0
        ],
        [
          2,
          0
        ]
      ]
    },
    "fthrow": {
      "strip": "animations/fthrow.png",
      "frameCount": 3,
      "frameWidth": 256,
      "frameHeight": 256,
      "sourceCells": [
        [
          0,
          0
        ],
        [
          1,
          0
        ],
        [
          2,
          0
        ]
      ]
    },
    "grab": {
      "strip": "animations/grab.png",
      "frameCount": 3,
      "frameWidth": 256,
      "frameHeight": 256,
      "sourceCells": [
        [
          0,
          0
        ],
        [
          1,
          0
        ],
        [
          2,
          0
        ]
      ]
    },
    "hurt": {
      "strip": "animations/hurt.png",
      "frameCount": 2,
      "frameWidth": 256,
      "frameHeight": 256,
      "sourceCells": [
        [
          0,
          0
        ],
        [
          1,
          0
        ]
      ]
    },
    "idle": {
      "strip": "animations/idle.png",
      "frameCount": 4,
      "frameWidth": 256,
      "frameHeight": 256,
      "sourceCells": [
        [
          0,
          0
        ],
        [
          1,
          0
        ],
        [
          2,
          0
        ],
        [
          3,
          0
        ]
      ]
    },
    "jab": {
      "strip": "animations/jab.png",
      "frameCount": 3,
      "frameWidth": 256,
      "frameHeight": 256,
      "sourceCells": [
        [
          0,
          0
        ],
        [
          1,
          0
        ],
        [
          2,
          0
        ]
      ]
    },
    "jab2": {
      "strip": "animations/jab2.png",
      "frameCount": 4,
      "frameWidth": 256,
      "frameHeight": 256,
      "sourceCells": [
        [
          0,
          0
        ],
        [
          1,
          0
        ],
        [
          2,
          0
        ],
        [
          3,
          0
        ]
      ]
    },
    "jab3": {
      "strip": "animations/jab3.png",
      "frameCount": 4,
      "frameWidth": 256,
      "frameHeight": 256,
      "sourceCells": [
        [
          0,
          0
        ],
        [
          1,
          0
        ],
        [
          2,
          0
        ],
        [
          3,
          0
        ]
      ]
    },
    "jump": {
      "strip": "animations/jump.png",
      "frameCount": 5,
      "frameWidth": 256,
      "frameHeight": 256,
      "sourceCells": [
        [
          0,
          0
        ],
        [
          1,
          0
        ],
        [
          2,
          0
        ],
        [
          3,
          0
        ],
        [
          4,
          0
        ]
      ]
    },
    "nair": {
      "strip": "animations/nair.png",
      "frameCount": 3,
      "frameWidth": 256,
      "frameHeight": 256,
      "sourceCells": [
        [
          0,
          0
        ],
        [
          1,
          0
        ],
        [
          2,
          0
        ]
      ]
    },
    "neutral_special": {
      "strip": "animations/neutral_special.png",
      "frameCount": 3,
      "frameWidth": 256,
      "frameHeight": 256,
      "sourceCells": [
        [
          0,
          0
        ],
        [
          1,
          0
        ],
        [
          2,
          0
        ]
      ]
    },
    "pummel": {
      "strip": "animations/pummel.png",
      "frameCount": 2,
      "frameWidth": 256,
      "frameHeight": 256,
      "sourceCells": [
        [
          0,
          0
        ],
        [
          1,
          0
        ]
      ]
    },
    "run": {
      "strip": "animations/run.png",
      "frameCount": 8,
      "frameWidth": 256,
      "frameHeight": 256,
      "sourceCells": [
        [
          0,
          0
        ],
        [
          1,
          0
        ],
        [
          2,
          0
        ],
        [
          3,
          0
        ],
        [
          4,
          0
        ],
        [
          5,
          0
        ],
        [
          6,
          0
        ],
        [
          7,
          0
        ]
      ]
    },
    "shield": {
      "strip": "animations/shield.png",
      "frameCount": 1,
      "frameWidth": 256,
      "frameHeight": 256,
      "sourceCells": [
        [
          0,
          0
        ]
      ]
    },
    "side_special": {
      "strip": "animations/side_special.png",
      "frameCount": 3,
      "frameWidth": 256,
      "frameHeight": 256,
      "sourceCells": [
        [
          0,
          0
        ],
        [
          1,
          0
        ],
        [
          2,
          0
        ]
      ]
    },
    "smash": {
      "strip": "animations/smash.png",
      "frameCount": 4,
      "frameWidth": 256,
      "frameHeight": 256,
      "sourceCells": [
        [
          0,
          0
        ],
        [
          1,
          0
        ],
        [
          2,
          0
        ],
        [
          3,
          0
        ]
      ]
    },
    "tilt": {
      "strip": "animations/tilt.png",
      "frameCount": 3,
      "frameWidth": 256,
      "frameHeight": 256,
      "sourceCells": [
        [
          0,
          0
        ],
        [
          1,
          0
        ],
        [
          2,
          0
        ]
      ]
    },
    "uair": {
      "strip": "animations/uair.png",
      "frameCount": 3,
      "frameWidth": 256,
      "frameHeight": 256,
      "sourceCells": [
        [
          0,
          0
        ],
        [
          1,
          0
        ],
        [
          2,
          0
        ]
      ]
    },
    "up_special": {
      "strip": "animations/up_special.png",
      "frameCount": 3,
      "frameWidth": 256,
      "frameHeight": 256,
      "sourceCells": [
        [
          0,
          0
        ],
        [
          1,
          0
        ],
        [
          2,
          0
        ]
      ]
    },
    "uthrow": {
      "strip": "animations/uthrow.png",
      "frameCount": 3,
      "frameWidth": 256,
      "frameHeight": 256,
      "sourceCells": [
        [
          0,
          0
        ],
        [
          1,
          0
        ],
        [
          2,
          0
        ]
      ]
    }
  }
}